{
  "parent": "minecraft:nether/root",
  "criteria": {
    "got_nether_fruit": {
      "conditions": {
        "items": [
          {
            "tag": "nears:nether_fruits"
          }
        ]
      },
      "trigger": "minecraft:inventory_changed"
    }
  },
  "display": {
    "announce_to_chat": true,
    "description": {
      "translate": "advancements.nether.symbiotic.description"
    },
    "frame": "task",
    "hidden": false,
    "icon": {
      "item": "nears:near"
    },
    "show_toast": true,
    "title": {
      "translate": "advancements.nether.symbiotic.title"
    }
  },
  "requirements": [
    [
      "got_nether_fruit"
    ]
  ],
  "rewards": {
    "experience": 2
  },
  "sends_telemetry_event": true
}